<?xml version="1.0" encoding="utf-8"?>
<CodeBlockFile xmlns:xsd="http://www.w3.org/2001/XMLSchema" xmlns:xsi="http://www.w3.org/2001/XMLSchema-instance" Id="52394d39-859e-46bd-ad16-83371aef5243" Language="Lua" Name="A_NPC_RUN" Type="Component" Source="None" ModifyTime="2022-08-24T01:01:23.7457685+07:00">
  <CoreVersion Major="0" Minor="2" />
  <ScriptVersion Major="1" Minor="0" />
  <Description />
  <Properties>
    <CodeBlockProperty Name="start_run" Type="boolean" DefaultValue="false" SyncDirection="All" />
    <CodeBlockProperty Name="speed" Type="number" DefaultValue="0.015" SyncDirection="All" />
    <CodeBlockProperty Name="diff" Type="number" DefaultValue="0" SyncDirection="All" />
    <CodeBlockProperty Name="boss" Type="Entity" DefaultValue="nil" SyncDirection="All" />
    <CodeBlockProperty Name="_time" Type="number" DefaultValue="0" SyncDirection="All" />
  </Properties>
  <Methods>
    <CodeBlockMethod Name="OnBeginPlay" ExecSpace="ServerOnly">
      <Return Type="void" SyncDirection="None" />
      <Code><![CDATA[

self.start_run = false
self.Entity.StateComponent:ChangeState("stand")

]]></Code>
    </CodeBlockMethod>
    <CodeBlockMethod Name="OnUpdate" ExecSpace="ServerOnly">
      <Return Type="void" SyncDirection="None" />
      <Arguments>
        <CodeBlockProperty Name="delta" Type="number" SyncDirection="None" />
      </Arguments>
      <Code><![CDATA[
self.boss  = _EntityService:GetEntityByPath("/maps/map01/monster-1014")

local diff = self.boss.TransformComponent.Position.x+5.5

self.diff = diff
if(self.Entity.TransformComponent.Position.x <= diff) then
	self.Entity.ChatBalloonComponent.AutoShowEnabled = true
self.start_run = true
end

if self.start_run == true then
self.Entity.SpriteRendererComponent.FlipX = true

local pos = self.Entity.TransformComponent.Position
pos.x = pos.x + self.speed
self.Entity.TransformComponent.Position = Vector3(pos.x,pos.y,pos.z)
	
end

]]></Code>
    </CodeBlockMethod>
  </Methods>
  <EntityEventHandlers>
    <CodeBlockEntityEventHandler Name="HandleTriggerEnterEvent" EventName="TriggerEnterEvent" Target="self" Scope="All">
      <Code><![CDATA[

-- Parameters
local TriggerBodyEntity = event.TriggerBodyEntity
--------------------------------------------------------


local stone = _EntityService:GetEntityByPath("/maps/map01/STONE")
--if TriggerBodyEntity.Name == stone.Name then
	  
--end
]]></Code>
    </CodeBlockEntityEventHandler>
  </EntityEventHandlers>
</CodeBlockFile>